noteboard/__init__.py
noteboard/__version__.py
noteboard/cli.py
noteboard/storage.py
noteboard/utils.py
noteboard-1.1.5.dist-info/LICENSE.txt
noteboard-1.1.5.dist-info/METADATA
noteboard-1.1.5.dist-info/WHEEL
noteboard-1.1.5.dist-info/entry_points.txt
noteboard-1.1.5.dist-info/top_level.txt
noteboard-1.1.5.dist-info/RECORD
