Metadata-Version: 2.1
Name: noteboard
Version: 1.1.5
Summary: Manage your notes & tasks in a tidy and fancy way.
Home-page: https://github.com/a1phat0ny/noteboard
Author: a1phat0ny
Author-email: tony.chan2342@gmail.com
License: MIT
Keywords: cli,todo,task,note,board,gzip,interactive,taskbook
Platform: UNKNOWN
Classifier: License :: OSI Approved :: MIT License
Classifier: Programming Language :: Python
Classifier: Programming Language :: Python :: 3
Classifier: Programming Language :: Python :: 3.6
Classifier: Programming Language :: Python :: Implementation :: CPython
Classifier: Programming Language :: Python :: Implementation :: PyPy
Requires-Python: >=3.6.0
Requires-Dist: colorama
